{
    "@context": [
        "https://www.w3.org/ns/csvw#",
        {
            "@language": "en",
            "dc": "https://purl.org/dc/terms/",
            "gml": "https://schemas.opengis.net/gml/",
            "wfs": "https://schemas.opengis.net/wfs/1.1.0/wfs.xsd",
            "xlink": "https://www.w3.org/1999/xlink/",
            "xsd": "https://www.w3.org/2001/XMLSchema#",
            "qudt": "https://qudt.org/schema/qudt/",
            "unit": "https://qudt.org/vocab/unit/",
            "openvocab": "https://vocab.org/open/",
            "rdf": "https://www.w3.org/1999/02/22-rdf-syntax-ns#",
            "rdfs": "https://www.w3.org/2000/01/rdf-schema#",
            "dcat": "https://www.w3.org/ns/dcat#",
            "prov": "https://www.w3.org/ns/prov#"
        }
    ],
    "dc:license": {
        "@id": "http://opendefinition.org/licenses/cc-by/"
    },
    "openvocab:versionnumber": 1,
    "tableSchema": {
        "columns": [
            {
                "datatype": "xsd:string",
                "required": "true",
                "name": "sector",
                "titles": "sector",
                "dc:description": "An economic classification or category that groups together similar industries or economic activities based on the goods or services they produce.",
                "qudt:unit": "unit:UNITLESS"
            },
            {
                "datatype": "xsd:decimal",
                "required": "true",
                "name": "shock",
                "titles": "shock",
                "dc:description": "Calculated value that represents the shock on each sector based on the appraisal values of the buildings and their associated failure probabilities.",
                "qudt:unit": "unit:UNITLESS"
            }
        ]
    },
    "url": "incore:capitalShocks",
    "dc:title": "incore:capitalShocks",
    "dc:description": "Aggregation of building functionality states to capital shocks per sector."
}